{
  "project_info": {
    "project_number": "707283006662",
    "firebase_url": "https://jae-firebase-map.firebaseio.com",
    "project_id": "jae-firebase-map",
    "storage_bucket": "jae-firebase-map.appspot.com"
  },
  "client": [
    {
      "client_info": {
        "mobilesdk_app_id": "1:707283006662:android:374b4af11ea6d701",
        "android_client_info": {
          "package_name": "com.hieuapp.rivchat"
        }
      },
      "oauth_client": [
        {
          "client_id": "707283006662-p519gsgbhjptft4q5aga2cnk5fstq6jt.apps.googleusercontent.com",
          "client_type": 3
        }
      ],
      "api_key": [
        {
          "current_key": "AIzaSyCBzGkirAnm24bvDmnPxu1K1Iq0HcyXJsc"
        }
      ],
      "services": {
        "analytics_service": {
          "status": 1
        },
        "appinvite_service": {
          "status": 1,
          "other_platform_oauth_client": []
        },
        "ads_service": {
          "status": 2
        }
      }
    }
  ],
  "configuration_version": "1"
}